.gitignore
CHANGES.md
CONTRIBUTORS.md
LICENSE.md
Makefile
README.md
TODO.md
setup.py
bobtemplates/__init__.py
bobtemplates.sixfeetup.egg-info/PKG-INFO
bobtemplates.sixfeetup.egg-info/SOURCES.txt
bobtemplates.sixfeetup.egg-info/dependency_links.txt
bobtemplates.sixfeetup.egg-info/not-zip-safe
bobtemplates.sixfeetup.egg-info/requires.txt
bobtemplates.sixfeetup.egg-info/top_level.txt
bobtemplates/sixfeetup/__init__.py
bobtemplates/sixfeetup/hooks.py
bobtemplates/sixfeetup/unified_buildout/.gitignore.bob
bobtemplates/sixfeetup/unified_buildout/.mrbob.ini
bobtemplates/sixfeetup/unified_buildout/Makefile
bobtemplates/sixfeetup/unified_buildout/README.md
bobtemplates/sixfeetup/unified_buildout/data-targets.txt
bobtemplates/sixfeetup/unified_buildout/fabfile.py.bob
bobtemplates/sixfeetup/unified_buildout/requirements.txt
bobtemplates/sixfeetup/unified_buildout/setup.py.bob
bobtemplates/sixfeetup/unified_buildout/version.txt
bobtemplates/sixfeetup/unified_buildout/+project_name+/__init__.py
bobtemplates/sixfeetup/unified_buildout/+project_name+/content/README.txt
bobtemplates/sixfeetup/unified_buildout/+project_name+/content/__init__.py.bob
bobtemplates/sixfeetup/unified_buildout/+project_name+/content/config.py.bob
bobtemplates/sixfeetup/unified_buildout/+project_name+/content/configure.zcml.bob
bobtemplates/sixfeetup/unified_buildout/+project_name+/content/browser/__init__.py
bobtemplates/sixfeetup/unified_buildout/+project_name+/content/browser/configure.zcml.bob
bobtemplates/sixfeetup/unified_buildout/+project_name+/content/content/__init__.py
bobtemplates/sixfeetup/unified_buildout/+project_name+/content/content/configure.zcml.bob
bobtemplates/sixfeetup/unified_buildout/+project_name+/content/interfaces/__init__.py
bobtemplates/sixfeetup/unified_buildout/+project_name+/content/portlets/__init__.py
bobtemplates/sixfeetup/unified_buildout/+project_name+/content/portlets/configure.zcml.bob
bobtemplates/sixfeetup/unified_buildout/+project_name+/content/profiles/default/metadata.xml
bobtemplates/sixfeetup/unified_buildout/+project_name+/content/profiles/default/portlets.xml
bobtemplates/sixfeetup/unified_buildout/+project_name+/content/profiles/default/types.xml
bobtemplates/sixfeetup/unified_buildout/+project_name+/content/tests/__init__.py
