Metadata-Version: 2.1
Name: bobtemplates.sixfeetup
Version: 2.1
Summary: Unified buildout template for Plone projects.
Home-page: https://github.com/sixfeetup/bobtemplates.sixfeetup
Author: Six Feet Up, Inc.
Author-email: info@sixfeetup.com
License: BSD
Keywords: web plone zope skeleton project buildout
Platform: UNKNOWN
Classifier: Environment :: Console
Classifier: Intended Audience :: Developers
Classifier: Natural Language :: English
Classifier: Operating System :: OS Independent
Classifier: Programming Language :: Python
Classifier: Framework :: Plone
Classifier: Development Status :: 5 - Production/Stable
Classifier: Topic :: Software Development :: Code Generators
Classifier: Topic :: Utilities
Classifier: License :: OSI Approved :: BSD License
Provides-Extra: test
